Metadata-Version: 2.1
Name: entropeer
Version: 0.1.1
Summary: Searches through files and directories for high entropy strings and secrets. 
Home-page: https://github.com/TheZ3ro/entropeer
Author: TheZero
Author-email: io@thezero.org
License: LGPLv3
Download-URL: https://github.com/TheZ3ro/entropeer/archive/0.1.1.tar.gz
Keywords: entropy,secrets,grep,recursive
Platform: UNKNOWN
Classifier: Environment :: Console
Classifier: Intended Audience :: Developers
Classifier: Intended Audience :: System Administrators
Classifier: License :: OSI Approved :: GNU Lesser General Public License v3 or later (LGPLv3+)
Classifier: Natural Language :: English
Classifier: Operating System :: MacOS
Classifier: Operating System :: Microsoft :: Windows
Classifier: Operating System :: POSIX
Classifier: Programming Language :: Python :: 3
Classifier: Programming Language :: Python :: 3.4
Classifier: Programming Language :: Python :: 3.5
Classifier: Programming Language :: Python :: 3.6
Classifier: Programming Language :: Python :: 3.7
Classifier: Programming Language :: Python :: 3.8
Classifier: Topic :: Security
